{"timestamp": 1771705363.9849463, "ttl_days": 30, "data": {"articles": [{"title": "Novice-friendly probes for the gathering and analysis of requirements and subsequent design of software", "authors": ["Francisco Lepe-Salazar", "Lizbeth Escobedo", "Tatsuo Nakajima"], "year": 2025, "publication": "Int. J. Hum. Comput. Stud.", "link": "https://doi.org/10.1016/j.ijhcs.2024.103405", "snippet": "Int. J. Hum. Comput. Stud., 2025, 10.1016/j.ijhcs.2024.103405", "source": "dblp", "result_id": "dblp:doi:10.1016/j.ijhcs.2024.103405"}, {"title": "Optical Character Recognition for Early Handwriting Legibility Assessment", "authors": ["Franceli L. Cibrian", "Kayla Anderson", "Yingchen 'Yuki' Chen", "Lauren Min", "Lizbeth Escobedo"], "year": 2025, "publication": "HCI (2)", "link": "https://doi.org/10.1007/978-3-031-93838-2_11", "snippet": "HCI (2), 2025, 10.1007/978-3-031-93838-2_11", "source": "dblp", "result_id": "dblp:doi:10.1007/978-3-031-93838-2_11"}, {"title": "Analyzing Handwriting Legibility in Children Using Smart Vs. Traditional Pen", "authors": ["Franceli L. Cibrian", "Lauren Min", "Yingchen 'Yuki' Chen", "Kayla Anderson", "Oscar Gutierrez", "Lizbeth Escobedo"], "year": 2024, "publication": "UCAmI", "link": "https://doi.org/10.1007/978-3-031-77571-0_51", "snippet": "UCAmI, 2024, 10.1007/978-3-031-77571-0_51", "source": "dblp", "result_id": "dblp:doi:10.1007/978-3-031-77571-0_51"}, {"title": "Designing a Stress and Anxiety Support Tool to Help Young Adults with Autism in Daily Living", "authors": ["Marcela Espinosa", "Lizbeth Escobedo"], "year": 2023, "publication": "Interact. Comput.", "link": "https://doi.org/10.1093/iwc/iwad012", "snippet": "Interact. Comput., 2023, 10.1093/iwc/iwad012", "source": "dblp", "result_id": "dblp:doi:10.1093/iwc/iwad012"}, {"title": "Ethics without IRB, is that possible? The case study of participatory sessions with ASD Children in Mexico", "authors": ["Lizbeth Escobedo", "Franceli L. Cibrian", "Monica Tentori"], "year": 2023, "publication": "UbiComp/ISWC Adjunct", "link": "https://doi.org/10.1145/3594739.3610729", "snippet": "UbiComp/ISWC Adjunct, 2023, 10.1145/3594739.3610729", "source": "dblp", "result_id": "dblp:doi:10.1145/3594739.3610729"}, {"title": "Research Methodologies across the Physical - Virtual Reality Spectrum", "authors": ["Rina R. Wehbe", "Mayra Donaji Barrera Machuca", "Lizbeth Escobedo"], "year": 2023, "publication": "UbiComp/ISWC Adjunct", "link": "https://doi.org/10.1145/3594739.3605104", "snippet": "UbiComp/ISWC Adjunct, 2023, 10.1145/3594739.3605104", "source": "dblp", "result_id": "dblp:doi:10.1145/3594739.3605104"}, {"title": "Understanding the challenges of deploying a milestone-tracking application in a cross-cultural context", "authors": ["Lizbeth Escobedo", "Rosa I. Arriaga"], "year": 2022, "publication": "Int. J. Hum. Comput. Stud.", "link": "https://doi.org/10.1016/j.ijhcs.2022.102801", "snippet": "Int. J. Hum. Comput. Stud., 2022, 10.1016/j.ijhcs.2022.102801", "source": "dblp", "result_id": "dblp:doi:10.1016/j.ijhcs.2022.102801"}, {"title": "SmarTasko: Supporting short and spontaneous activities of daily living of ADHD individuals", "authors": ["Marcos Moroyoqui", "David Espina", "Hector Osuna", "Lizbeth Escobedo"], "year": 2022, "publication": "MexIHC", "link": "https://doi.org/10.1145/3565494.3565500", "snippet": "MexIHC, 2022, 10.1145/3565494.3565500", "source": "dblp", "result_id": "dblp:doi:10.1145/3565494.3565500"}, {"title": "9th Mexican International Conference on Human-Computer Interaction, MexIHC 2022, Virtual Event, Mexico, November 16-18, 2022", "authors": ["Cuauht\u00e9moc Rivera Loaiza", "Silvia Berenice Fajardo Flores", "Laura S. Gayt\u00e1n-Lugo", "Lizbeth Escobedo"], "year": 2022, "publication": "MexIHC", "link": "https://doi.org/10.1145/3565494", "snippet": "MexIHC, 2022, 10.1145/3565494", "source": "dblp", "result_id": "dblp:doi:10.1145/3565494"}, {"title": "A BCI video game using neurofeedback improves the attention of children with autism", "authors": ["Jos\u00e9 Mercado", "Lizbeth Escobedo", "Monica Tentori"], "year": 2021, "publication": "J. Multimodal User Interfaces", "link": "https://doi.org/10.1007/s12193-020-00339-7", "snippet": "J. Multimodal User Interfaces, 2021, 10.1007/s12193-020-00339-7", "source": "dblp", "result_id": "dblp:doi:10.1007/s12193-020-00339-7"}, {"title": "PenSando: Developing a Smartpen Assessing Handwriting Skills for Children", "authors": ["Franceli L. Cibrian", "Oscar Gutierrez", "Lizbeth Escobedo"], "year": 2021, "publication": "CLIHC", "link": "https://doi.org/10.1145/3488392.3488393", "snippet": "CLIHC, 2021, 10.1145/3488392.3488393", "source": "dblp", "result_id": "dblp:doi:10.1145/3488392.3488393"}, {"title": "SATORI: a support tool for young adults with autism to self-manage stress and anxiety", "authors": ["Marcela Espinosa", "Lizbeth Escobedo"], "year": 2021, "publication": "CLIHC", "link": "https://doi.org/10.1145/3488392.3488394", "snippet": "CLIHC, 2021, 10.1145/3488392.3488394", "source": "dblp", "result_id": "dblp:doi:10.1145/3488392.3488394"}, {"title": "Towards an automatic coding of observational studies: Coding neurofeedback therapies of children with autism", "authors": ["V\u00edctor R. L\u00f3pez-L\u00f3pez", "Lizbeth Escobedo", "Leonardo Trujillo"], "year": 2020, "publication": "Expert Syst. J. Knowl. Eng.", "link": "https://doi.org/10.1111/exsy.12572", "snippet": "Expert Syst. J. Knowl. Eng., 2020, 10.1111/exsy.12572", "source": "dblp", "result_id": "dblp:doi:10.1111/exsy.12572"}, {"title": "Developing and evaluating a BCI video game for neurofeedback training: the case of autism", "authors": ["Jos\u00e9 Mercado", "Ismael Edrein Espinosa-Curiel", "Lizbeth Escobedo", "Monica Tentori"], "year": 2019, "publication": "Multim. Tools Appl.", "link": "https://doi.org/10.1007/s11042-018-6916-2", "snippet": "Multim. Tools Appl., 2019, 10.1007/s11042-018-6916-2", "source": "dblp", "result_id": "dblp:doi:10.1007/s11042-018-6916-2"}, {"title": "Towards early and automatic detection of Urinary Infection during pregnancy", "authors": ["Lizbeth Escobedo", "Ad\u00e1n Hirales-Carbajal"], "year": 2019, "publication": "EAI Endorsed Trans. Pervasive Health Technol.", "link": "https://doi.org/10.4108/eai.13-7-2018.162810", "snippet": "EAI Endorsed Trans. Pervasive Health Technol., 2019, 10.4108/eai.13-7-2018.162810", "source": "dblp", "result_id": "dblp:doi:10.4108/eai.13-7-2018.162810"}, {"title": "ActEarly: a bi-national evaluation study of a mobile application for tracking developmental milestones", "authors": ["Vicente Armenta", "Laurel Warrell", "Nazneen", "Lizbeth Escobedo", "Rosa I. Arriaga"], "year": 2019, "publication": "CLIHC", "link": "https://doi.org/10.1145/3358961.3358963", "snippet": "CLIHC, 2019, 10.1145/3358961.3358963", "source": "dblp", "result_id": "dblp:doi:10.1145/3358961.3358963"}, {"title": "UTIW: Urinary Tract Infection Workflow System towards early and automatic detection of Urinary Infection during pregnancy", "authors": ["Ad\u00e1n Hirales-Carbajal", "Lizbeth Escobedo"], "year": 2019, "publication": "PervasiveHealth", "link": "https://doi.org/10.1145/3329189.3329238", "snippet": "PervasiveHealth, 2019, 10.1145/3329189.3329238", "source": "dblp", "result_id": "dblp:doi:10.1145/3329189.3329238"}, {"title": "A Step towards Identifying the Sound Preferences of Children with Autism", "authors": ["Franceli L. Cibrian", "Jos\u00e9 Mercado", "Lizbeth Escobedo", "Monica Tentori"], "year": 2018, "publication": "PervasiveHealth", "link": "https://doi.org/10.1145/3240925.3240958", "snippet": "PervasiveHealth, 2018, 10.1145/3240925.3240958", "source": "dblp", "result_id": "dblp:doi:10.1145/3240925.3240958"}, {"title": "Proceedings of the 7th Mexican Conference on Human-Computer Interaction, MexIHC '18, Merida, Mexico, October 29-31, 2018", "authors": ["Edgar Cambranes", "Lizbeth Escobedo", "Omar Sosa-Tzec", "Juan Pablo-Garcia", "Jes\u00fas Favela"], "year": 2018, "publication": "MexIHC", "link": "https://doi.org/10.1145/3293578", "snippet": "MexIHC, 2018, 10.1145/3293578", "source": "dblp", "result_id": "dblp:doi:10.1145/3293578"}, {"title": "Pervasive Displays in Classrooms of Children with Severe Autism", "authors": ["Monica Tentori", "Lizbeth Escobedo", "Carlos Hern\u00e1ndez", "Aleksandar Matic", "Gillian R. Hayes"], "year": 2016, "publication": "IEEE Pervasive Comput.", "link": "https://doi.org/10.1109/MPRV.2016.49", "snippet": "IEEE Pervasive Comput., 2016, 10.1109/mprv.2016.49", "source": "dblp", "result_id": "dblp:doi:10.1109/mprv.2016.49"}, {"title": "A Smart Environment for Children with Autism", "authors": ["Monica Tentori", "Lizbeth Escobedo", "Gabriela Balderas"], "year": 2015, "publication": "IEEE Pervasive Comput.", "link": "https://doi.org/10.1109/MPRV.2015.22", "snippet": "IEEE Pervasive Comput., 2015, 10.1109/mprv.2015.22", "source": "dblp", "result_id": "dblp:doi:10.1109/mprv.2015.22"}, {"title": "Reflections from a Long-term Deployment Study to Design Novel Interactive Surfaces for Children with Autism", "authors": ["Franceli Linney Cibrian", "Deysi Helen Ortega", "Lizbeth Escobedo", "Monica Tentori"], "year": 2015, "publication": "AmIHEALTH", "link": "https://doi.org/10.1007/978-3-319-26508-7_17", "snippet": "AmIHEALTH, 2015, 10.1007/978-3-319-26508-7_17", "source": "dblp", "result_id": "dblp:doi:10.1007/978-3-319-26508-7_17"}, {"title": "Flexibility in Biopharmaceutical Manufacturing Using Particle Swarm Algorithms and Genetic Algorithms", "authors": ["Youness El Hamzaoui", "Ali Bassam", "Mohamed Abatal", "Jos\u00e9 A. Rodr\u00edguez", "Miguel Aurelio Duarte-Villase\u00f1or", "Lizbeth Escobedo", "Sergio A. Puga"], "year": 2015, "publication": "NEO", "link": "https://doi.org/10.1007/978-3-319-44003-3_7", "snippet": "NEO, 2015, 10.1007/978-3-319-44003-3_7", "source": "dblp", "result_id": "dblp:doi:10.1007/978-3-319-44003-3_7"}, {"title": "Promoting Self-Reflection of Social Isolation Through Persuasive Mobile Technologies: The Case of Mother Caregivers of Children With Cancer", "authors": ["Carolina Fuentes", "Carlos Hern\u00e1ndez", "Lizbeth Escobedo", "Valeria Herskovic", "Monica Tentori"], "year": 2014, "publication": "Int. J. Hum. Comput. Interact.", "link": "https://doi.org/10.1080/10447318.2014.927279", "snippet": "Int. J. Hum. Comput. Interact., 2014, 10.1080/10447318.2014.927279", "source": "dblp", "result_id": "dblp:doi:10.1080/10447318.2014.927279"}, {"title": "Using Augmented Reality to Help Children with Autism Stay Focused", "authors": ["Lizbeth Escobedo", "Monica Tentori", "Eduardo Quintana", "Jes\u00fas Favela", "Daniel Garcia-Rosas"], "year": 2014, "publication": "IEEE Pervasive Comput.", "link": "https://doi.org/10.1109/MPRV.2014.19", "snippet": "IEEE Pervasive Comput., 2014, 10.1109/mprv.2014.19", "source": "dblp", "result_id": "dblp:doi:10.1109/mprv.2014.19"}, {"title": "Smart objects to support the discrimination training of children with autism", "authors": ["Lizbeth Escobedo", "Catalina Ibarra", "Jehu Hernandez", "Mariana Alvelais", "Monica Tentori"], "year": 2014, "publication": "Pers. Ubiquitous Comput.", "link": "https://doi.org/10.1007/s00779-013-0750-3", "snippet": "Pers. Ubiquitous Comput., 2014, 10.1007/s00779-013-0750-3", "source": "dblp", "result_id": "dblp:doi:10.1007/s00779-013-0750-3"}, {"title": "SensoryPaint: a natural user interface supporting sensory integration in children with neurodevelopmental disorders", "authors": ["Kathryn E. Ringland", "Rodrigo Zalapa", "Megan Neal", "Lizbeth Escobedo", "Monica E. Tentori", "Gillian R. Hayes"], "year": 2014, "publication": "CHI Extended Abstracts", "link": "https://doi.org/10.1145/2559206.2581249", "snippet": "CHI Extended Abstracts, 2014, 10.1145/2559206.2581249", "source": "dblp", "result_id": "dblp:doi:10.1145/2559206.2581249"}, {"title": "SensoryPaint: a multimodal sensory intervention for children with neurodevelopmental disorders", "authors": ["Kathryn E. Ringland", "Rodrigo Zalapa", "Megan Neal", "Lizbeth Escobedo", "Monica Tentori", "Gillian R. Hayes"], "year": 2014, "publication": "UbiComp", "link": "https://doi.org/10.1145/2632048.2632065", "snippet": "UbiComp, 2014, 10.1145/2632048.2632065", "source": "dblp", "result_id": "dblp:doi:10.1145/2632048.2632065"}, {"title": "Mobile Augmented Reality to Support Teachers of Children with Autism", "authors": ["Lizbeth Escobedo", "Monica Tentori"], "year": 2014, "publication": "UCAmI", "link": "https://doi.org/10.1007/978-3-319-13102-3_12", "snippet": "UCAmI, 2014, 10.1007/978-3-319-13102-3_12", "source": "dblp", "result_id": "dblp:doi:10.1007/978-3-319-13102-3_12"}, {"title": "MOSOCO: a mobile assistive tool to support children with autism practicing social skills in real-life situations", "authors": ["Lizbeth Escobedo", "David H. Nguyen", "LouAnne E. Boyd", "Sen H. Hirano", "Alejandro Rangel", "Daniel Garcia-Rosas", "Monica Tentori", "Gillian R. Hayes"], "year": 2012, "publication": "CHI", "link": "https://doi.org/10.1145/2207676.2208649", "snippet": "CHI, 2012, 10.1145/2207676.2208649", "source": "dblp", "result_id": "dblp:doi:10.1145/2207676.2208649"}, {"title": "Object and Gesture Recognition to Assist Children with Autism during the Discrimination Training", "authors": ["Eduardo Quintana", "Catalina Ibarra", "Lizbeth Escobedo", "Monica Tentori", "Jes\u00fas Favela"], "year": 2012, "publication": "CIARP", "link": "https://doi.org/10.1007/978-3-642-33275-3_108", "snippet": "CIARP, 2012, 10.1007/978-3-642-33275-3_108", "source": "dblp", "result_id": "dblp:doi:10.1007/978-3-642-33275-3_108"}]}}