{"timestamp": 1771733533.0991282, "ttl_days": 90, "data": {"indexed": {"date-parts": [[2026, 1, 30]], "date-time": "2026-01-30T06:21:49Z", "timestamp": 1769754109898, "version": "3.49.0"}, "reference-count": 54, "publisher": "Elsevier BV", "license": [{"start": {"date-parts": [[2022, 11, 1]], "date-time": "2022-11-01T00:00:00Z", "timestamp": 1667260800000}, "content-version": "tdm", "delay-in-days": 0, "URL": "https://www.elsevier.com/tdm/userlicense/1.0/"}, {"start": {"date-parts": [[2022, 11, 1]], "date-time": "2022-11-01T00:00:00Z", "timestamp": 1667260800000}, "content-version": "tdm", "delay-in-days": 0, "URL": "https://www.elsevier.com/legal/tdmrep-license"}, {"start": {"date-parts": [[2022, 11, 1]], "date-time": "2022-11-01T00:00:00Z", "timestamp": 1667260800000}, "content-version": "stm-asf", "delay-in-days": 0, "URL": "https://doi.org/10.15223/policy-017"}, {"start": {"date-parts": [[2022, 11, 1]], "date-time": "2022-11-01T00:00:00Z", "timestamp": 1667260800000}, "content-version": "stm-asf", "delay-in-days": 0, "URL": "https://doi.org/10.15223/policy-037"}, {"start": {"date-parts": [[2022, 11, 1]], "date-time": "2022-11-01T00:00:00Z", "timestamp": 1667260800000}, "content-version": "stm-asf", "delay-in-days": 0, "URL": "https://doi.org/10.15223/policy-012"}, {"start": {"date-parts": [[2022, 11, 1]], "date-time": "2022-11-01T00:00:00Z", "timestamp": 1667260800000}, "content-version": "stm-asf", "delay-in-days": 0, "URL": "https://doi.org/10.15223/policy-029"}, {"start": {"date-parts": [[2022, 11, 1]], "date-time": "2022-11-01T00:00:00Z", "timestamp": 1667260800000}, "content-version": "stm-asf", "delay-in-days": 0, "URL": "https://doi.org/10.15223/policy-004"}], "content-domain": {"domain": ["elsevier.com", "sciencedirect.com"], "crossmark-restriction": true}, "published-print": {"date-parts": [[2022, 11]]}, "DOI": "10.1016/j.jbusres.2022.05.066", "type": "journal-article", "created": {"date-parts": [[2022, 6, 15]], "date-time": "2022-06-15T19:04:34Z", "timestamp": 1655319874000}, "page": "134-146", "update-policy": "https://doi.org/10.1016/elsevier_cm_policy", "source": "Crossref", "is-referenced-by-count": 26, "special_numbering": "C", "title": "Disruptive innovation: Designing business platforms for new financial services", "prefix": "10.1016", "volume": "150", "author": [{"given": "Henry", "family": "Agyei-Boapeah", "sequence": "first", "affiliation": []}, {"ORCID": "https://orcid.org/0000-0001-6367-0560", "authenticated-orcid": false, "given": "Richard", "family": "Evans", "sequence": "additional", "affiliation": []}, {"ORCID": "https://orcid.org/0000-0003-2240-5327", "authenticated-orcid": false, "given": "Tahir M", "family": "Nisar", "sequence": "additional", "affiliation": []}], "member": "78", "reference": [{"issue": "3", "key": "10.1016/j.jbusres.2022.05.066_b0005", "first-page": "1", "article-title": "Customer satisfaction in microfinance institutions: Insights from Ghana", "volume": "31", "author": "Agyei-Boapeah", "year": "2020", "journal-title": "Enterprise Development & Microfinance"}, {"issue": "1", "key": "10.1016/j.jbusres.2022.05.066_b0010", "doi-asserted-by": "crossref", "first-page": "99", "DOI": "10.1177/014920639101700108", "article-title": "Firm resources and sustained competitive advantage", "volume": "17", "author": "Barney", "year": "1991", "journal-title": "Journal of Management"}, {"key": "10.1016/j.jbusres.2022.05.066_b0015", "article-title": "Digital platform openness: Drivers, dimensions and outcomes", "author": "Broekhuizen", "year": "2019", "journal-title": "Journal of Business Research"}, {"key": "10.1016/j.jbusres.2022.05.066_b0020", "unstructured": "Botsman, R. (2015) Defining the sharing economy: What is collaborative consumption \u2013 And what is isn\u2019t?. Available from: http://www.fastcoexist.com/3046119/defining-the-sharingeconomy-what-is-collaborative-consumption-and-what-isnt [Accessed 11 March 2021]."}, {"key": "10.1016/j.jbusres.2022.05.066_b0025", "first-page": "12", "article-title": "How to avoid platform traps", "volume": "57", "author": "Cennamo", "year": "2015", "journal-title": "Sloan Management Review"}, {"key": "10.1016/j.jbusres.2022.05.066_b0030", "article-title": "How interaction experience enhances customer engagement in smart speaker devices? The moderation of gendered voice and product smartness", "volume": "Vol. ahead-of-print No", "author": "Chen", "year": "2021", "journal-title": "Journal of Research in Interactive Marketing"}, {"key": "10.1016/j.jbusres.2022.05.066_b0035", "article-title": "Platform scale, How an emerging business model helps startups build large empires with minimum investment", "author": "Choudary", "year": "2015", "journal-title": "Platform Thinking Labs Pte. Ltd."}, {"key": "10.1016/j.jbusres.2022.05.066_b0040", "unstructured": "Christensen, C., Raynor, M. and McDonald, R. (2015) What is disruptive innovation? Harvard Business Review. December 2015 Issue."}, {"issue": "3", "key": "10.1016/j.jbusres.2022.05.066_b0045", "first-page": "45", "article-title": "Coping with Hypercompetition: Utilizing the New 7S's Framework", "volume": "9", "author": "D'Aveni", "year": "1995", "journal-title": "The Academy of Management Executive"}, {"issue": "12", "key": "10.1016/j.jbusres.2022.05.066_b0050", "doi-asserted-by": "crossref", "first-page": "1504", "DOI": "10.1287/mnsc.35.12.1504", "article-title": "Asset stock accumulation and sustainability of competitive advantage", "volume": "35", "author": "Dierickx", "year": "1989", "journal-title": "Management Science"}, {"issue": "6", "key": "10.1016/j.jbusres.2022.05.066_b0055", "first-page": "1", "article-title": "Network embeddedness as a dependence-balancing mechanism in developing markets: Differential effects for channel partners with asymmetric dependencies", "volume": "47", "author": "Dong", "year": "2018", "journal-title": "Journal of the Academy of Marketing Science"}, {"issue": "1", "key": "10.1016/j.jbusres.2022.05.066_b0060", "doi-asserted-by": "crossref", "DOI": "10.1007/s11187-019-00210-4", "article-title": "What impact does equity crowdfunding have on small innovation and growth? An empirical study", "volume": "56", "author": "Eldridge", "year": "2021", "journal-title": "Small Business Economics"}, {"issue": "5", "key": "10.1016/j.jbusres.2022.05.066_b0065", "doi-asserted-by": "crossref", "first-page": "395", "DOI": "10.1016/j.emj.2007.08.005", "article-title": "How to sustain the customer experience: An overview of experience components that co-create value with the customer", "volume": "25", "author": "Gentile", "year": "2007", "journal-title": "European Management Journal"}, {"key": "10.1016/j.jbusres.2022.05.066_b0070", "unstructured": "Gordon, K. and McCarthy. (2014) The state of small business lending: credit access during the recovery and how technology may change the game. Harvard Business School."}, {"key": "10.1016/j.jbusres.2022.05.066_b0075", "doi-asserted-by": "crossref", "first-page": "12", "DOI": "10.1111/j.1540-5885.2005.00176.x", "article-title": "The usefulness of measuring disruptiveness of innovations ex post in making ex ante predictions", "volume": "23", "author": "Govindarajan", "year": "2006", "journal-title": "The Journal of Product Innovation Management"}, {"key": "10.1016/j.jbusres.2022.05.066_b0080", "unstructured": "Haycock, J. and Richmond, S. (2015) Bye Bye Banks? How retail banks are being displaced, diminished and disintermediated by tech startups \u2013 and what they can do to survive. United Kingdom | London. Wunderkammer, Adaptive Lab."}, {"issue": "2", "key": "10.1016/j.jbusres.2022.05.066_b0085", "doi-asserted-by": "crossref", "first-page": "111", "DOI": "10.1108/17542731111110195", "article-title": "The theory of attractive quality and experience offerings", "volume": "23", "author": "H\u00f6gstr\u00f6m", "year": "2011", "journal-title": "The TQM Journal"}, {"key": "10.1016/j.jbusres.2022.05.066_b0090", "series-title": "Managing our hub economy", "first-page": "84", "author": "Iansiti", "year": "2017"}, {"key": "10.1016/j.jbusres.2022.05.066_b0095", "series-title": "Hospitality marketing and consumer behavior: Creating memorable experiences", "author": "Jauhari", "year": "2017"}, {"issue": "1", "key": "10.1016/j.jbusres.2022.05.066_b0100", "doi-asserted-by": "crossref", "first-page": "5", "DOI": "10.1108/09604521111100225", "article-title": "The customer experience: A road-map for improvement", "volume": "21", "author": "Johnston", "year": "2011", "journal-title": "Managing Service Quality: An International Journal"}, {"issue": "23", "key": "10.1016/j.jbusres.2022.05.066_b0105", "first-page": "42", "article-title": "Reflexivity: Promoting rigour in qualitative research", "volume": "23", "author": "Jootun", "year": "2009", "journal-title": "Nursing Standard"}, {"issue": "4", "key": "10.1016/j.jbusres.2022.05.066_b0110", "doi-asserted-by": "crossref", "first-page": "497", "DOI": "10.1509/jmr.15.0044", "article-title": "Competitive Advantage Through Engagement", "volume": "53", "author": "Kumar", "year": "2016", "journal-title": "Journal of Marketing Research"}, {"key": "10.1016/j.jbusres.2022.05.066_b0115", "article-title": "How can autonomy improve consumer experience when interacting with smart products?", "author": "Lucia-Palacios", "year": "2021", "journal-title": "Journal of Research in Interactive Marketing, Vol. ahead-of-print No. ahead-of-print."}, {"issue": "2", "key": "10.1016/j.jbusres.2022.05.066_b0120", "doi-asserted-by": "crossref", "first-page": "92", "DOI": "10.1177/0008125617695285", "article-title": "Managing customer relations: A better way to manage customer experience: Lessons from the royal bank of scotland", "volume": "59", "author": "Maklan", "year": "2017", "journal-title": "California Management Review"}, {"issue": "7", "key": "10.1016/j.jbusres.2022.05.066_b0125", "doi-asserted-by": "crossref", "first-page": "397", "DOI": "10.1108/07363760610712939", "article-title": "Lasting customer loyalty: A total customer experience approach", "volume": "23", "author": "Mascarenhas", "year": "2006", "journal-title": "Journal of Consumer Marketing"}, {"key": "10.1016/j.jbusres.2022.05.066_b0130", "unstructured": "Mitr\u0119ga-Niestr\u00f3j, K. (2013) The sharing economy and collaborative finance \u2013 outline of the problems.Available from: http://www.ue.katowice.pl/fileadmin/_migrated/content_uploads/1_K.MitregaNiestroj_Th Sharing_Economy....pdf [Accessed 7 February 2021]."}, {"key": "10.1016/j.jbusres.2022.05.066_b0135", "doi-asserted-by": "crossref", "first-page": "520", "DOI": "10.1016/j.jbusres.2019.06.037", "article-title": "On the costs of digital entrepreneurship: Role conflict, stress, and venture performance in digital platform-based ecosystems", "volume": "125", "author": "Nambisan", "year": "2021", "journal-title": "Journal of Business Research"}, {"key": "10.1016/j.jbusres.2022.05.066_b0140", "article-title": "Customer engagement and value co-creation/destruction: The internal fostering and hindering factors and actors in the tourist/hotel experience", "volume": "Vol. ahead-of-print No", "author": "Nangpiire", "year": "2021", "journal-title": "Journal of Research in Interactive Marketing"}, {"key": "10.1016/j.jbusres.2022.05.066_b0145", "series-title": "Platform Revolution; How networked markets are transforming the economy and how to make them work for you", "author": "Parker", "year": "2016"}, {"issue": "1", "key": "10.1016/j.jbusres.2022.05.066_b0150", "doi-asserted-by": "crossref", "first-page": "68", "DOI": "10.1108/JRIM-10-2020-0214", "article-title": "Enhancing the value co-creation process: Artificial intelligence and mobile banking service platforms", "volume": "15", "author": "Payne", "year": "2021", "journal-title": "Journal of Research in Interactive Marketing"}, {"issue": "2", "key": "10.1016/j.jbusres.2022.05.066_b0155", "doi-asserted-by": "crossref", "first-page": "200", "DOI": "10.1108/JRIM-12-2020-0252", "article-title": "Digital servitization value co-creation framework for AI services: A research agenda for digital transformation in financial service ecosystems", "volume": "15", "author": "Payne", "year": "2021", "journal-title": "Journal of Research in Interactive Marketing"}, {"issue": "2", "key": "10.1016/j.jbusres.2022.05.066_b0160", "doi-asserted-by": "crossref", "first-page": "269", "DOI": "10.1108/JRIM-10-2019-0159", "article-title": "One size doesn\u2019t fit all: A uses and gratifications analysis of social media platforms", "volume": "14", "author": "Pelletier", "year": "2020", "journal-title": "Journal of Research in Interactive Marketing"}, {"key": "10.1016/j.jbusres.2022.05.066_b0165", "first-page": "97", "article-title": "Welcome to the experience economy", "volume": "76", "author": "Pine", "year": "1998", "journal-title": "Harvard Business Review"}, {"key": "10.1016/j.jbusres.2022.05.066_b0170", "doi-asserted-by": "crossref", "first-page": "241", "DOI": "10.1016/j.ijpe.2015.07.037", "article-title": "The strategic fit between innovation strategies and business environment in delivering business performance", "volume": "171", "author": "Prajogo", "year": "2016", "journal-title": "International Journal of Production Economics"}, {"issue": "3", "key": "10.1016/j.jbusres.2022.05.066_b0175", "doi-asserted-by": "crossref", "first-page": "337", "DOI": "10.1108/JRIM-08-2019-0138", "article-title": "Fostering brand\u2013consumer interactions in social media: The role of social media uses and gratifications", "volume": "14", "author": "Qin", "year": "2020", "journal-title": "Journal of Research in Interactive Marketing"}, {"issue": "10", "key": "10.1016/j.jbusres.2022.05.066_b0180", "first-page": "100", "article-title": "Building the co-creative enterprise", "volume": "88", "author": "Ramaswamy", "year": "2010", "journal-title": "Harvard Business Review"}, {"issue": "1", "key": "10.1016/j.jbusres.2022.05.066_b0185", "doi-asserted-by": "crossref", "first-page": "93", "DOI": "10.1177/1094670507303232", "article-title": "Understanding frequent switching patterns", "volume": "10", "author": "Roos", "year": "2007", "journal-title": "Journal of Service Research"}, {"key": "10.1016/j.jbusres.2022.05.066_b0190", "doi-asserted-by": "crossref", "first-page": "347", "DOI": "10.1111/j.1540-5885.2008.00306.x", "article-title": "When is a disruptive innovation disruptive?", "volume": "25", "author": "Schmidt", "year": "2008", "journal-title": "The Journal of Product Innovation Management"}, {"issue": "2", "key": "10.1016/j.jbusres.2022.05.066_b0195", "first-page": "144", "article-title": "Welcome to the world of services management", "volume": "18", "author": "Schneider", "year": "2004", "journal-title": "The Academy of Management Executive"}, {"issue": "2", "key": "10.1016/j.jbusres.2022.05.066_b0200", "doi-asserted-by": "crossref", "first-page": "73", "DOI": "10.1108/09590550010315223", "article-title": "An examination of the relationship between service quality, customer satisfaction, and store loyalty", "volume": "28", "author": "Sivadas", "year": "2000", "journal-title": "International Journal of Retail & Distribution Management"}, {"key": "10.1016/j.jbusres.2022.05.066_b0205", "series-title": "Managing Innovation. Integrating Technological, Market and Organizational Change", "author": "Tidd", "year": "2013"}, {"key": "10.1016/j.jbusres.2022.05.066_b0210", "series-title": "Platform ecosystem: Aligning architecture, governance, and strategy", "author": "Tiwana", "year": "2013"}, {"issue": "2", "key": "10.1016/j.jbusres.2022.05.066_b0215", "doi-asserted-by": "crossref", "first-page": "358", "DOI": "10.1016/j.jinteco.2014.08.004", "article-title": "Does trade globalization induce or inhibit corporate transparency? Unbundling the growth potential and product market competition channels", "volume": "94", "author": "Tong", "year": "2014", "journal-title": "Journal of International Economics"}, {"key": "10.1016/j.jbusres.2022.05.066_b0220", "doi-asserted-by": "crossref", "unstructured": "Tseng, M., Hu, S. J. and Wang, Y. (2014) Mass customization IN: Laperri\u00e8re, L. and Reinhart, G. (eds.) CIRP Encyclopedia of Production Engineering. New York: Springer Publishing Company, 836-843.", "DOI": "10.1007/978-3-642-20617-7_16701"}, {"issue": "4", "key": "10.1016/j.jbusres.2022.05.066_b0225", "doi-asserted-by": "crossref", "first-page": "1367", "DOI": "10.1016/j.annals.2011.03.009", "article-title": "Exploring the essence of memorable tourism experiences", "volume": "38", "author": "Tung", "year": "2011", "journal-title": "Annals of Tourism Research"}, {"key": "10.1016/j.jbusres.2022.05.066_b0230", "first-page": "54", "article-title": "(2016) Pipelines, platforms, and the new rules of strategy", "volume": "R1604C", "author": "Van Alstyne", "year": "2016", "journal-title": "Harvard Business Review"}, {"issue": "12", "key": "10.1016/j.jbusres.2022.05.066_b0235", "doi-asserted-by": "crossref", "first-page": "2431", "DOI": "10.1016/j.jbusres.2013.05.031", "article-title": "The moderating role of managerial ties in market orientation and innovation: An Asian perspective", "volume": "66", "author": "Wang", "year": "2013", "journal-title": "Journal of Business Research"}, {"issue": "7", "key": "10.1016/j.jbusres.2022.05.066_b0240", "doi-asserted-by": "crossref", "first-page": "819", "DOI": "10.1016/j.indmarman.2008.01.008", "article-title": "The significance of trust and renqing in the long-term orientation of Chinese business-to-business relationships", "volume": "37", "author": "Wang", "year": "2008", "journal-title": "Industrial Marketing Management"}, {"issue": "1", "key": "10.1016/j.jbusres.2022.05.066_b0245", "doi-asserted-by": "crossref", "first-page": "1", "DOI": "10.1108/JRIM-03-2021-270", "article-title": "New frontiers and future directions in interactive marketing: Inaugural Editorial", "volume": "15", "author": "Wang", "year": "2021", "journal-title": "Journal of Research in Interactive Marketing"}, {"issue": "12", "key": "10.1016/j.jbusres.2022.05.066_b0250", "first-page": "56", "article-title": "Surviving disruption", "volume": "90", "author": "Wessel", "year": "2012", "journal-title": "Harvard Business Review"}, {"key": "10.1016/j.jbusres.2022.05.066_b0255", "doi-asserted-by": "crossref", "first-page": "435", "DOI": "10.1111/j.1468-2370.2009.00272.x", "article-title": "A reflective review of disrupted innovation theory", "volume": "12", "author": "Yu", "year": "2010", "journal-title": "International Journal of Management Review"}, {"key": "10.1016/j.jbusres.2022.05.066_b0260", "article-title": "Predicting value cocreation behavior in social media via integrating uses and gratifications paradigm and theory of planned behavior", "volume": "Vol. ahead-of-print No", "author": "Zadeh", "year": "2022", "journal-title": "Journal of Research in Interactive Marketing"}, {"key": "10.1016/j.jbusres.2022.05.066_b0265", "doi-asserted-by": "crossref", "first-page": "294", "DOI": "10.1016/j.jbusres.2016.12.025", "article-title": "The dyadic structure of exchange partners' governing-agency social capital and opportunism in buyer\u2013supplier relationships", "volume": "78", "author": "Zeng", "year": "2017", "journal-title": "Journal of Business Research"}, {"key": "10.1016/j.jbusres.2022.05.066_b0270", "doi-asserted-by": "crossref", "unstructured": "Zhang, H. and Ma, Z. (2021), Is my design better? A co-creation perspective for online fashion design, Journal of Research in Interactive Marketing, Vol. ahead-of-print No. ahead-of-print.https://doi.org/10.1108/JRIM-05-2021-0132.", "DOI": "10.1108/JRIM-05-2021-0132"}], "container-title": "Journal of Business Research", "original-title": [], "language": "en", "link": [{"URL": "https://api.elsevier.com/content/article/PII:S0148296322005082?httpAccept=text/xml", "content-type": "text/xml", "content-version": "vor", "intended-application": "text-mining"}, {"URL": "https://api.elsevier.com/content/article/PII:S0148296322005082?httpAccept=text/plain", "content-type": "text/plain", "content-version": "vor", "intended-application": "text-mining"}], "deposited": {"date-parts": [[2025, 9, 27]], "date-time": "2025-09-27T07:51:05Z", "timestamp": 1758959465000}, "score": 1, "resource": {"primary": {"URL": "https://linkinghub.elsevier.com/retrieve/pii/S0148296322005082"}}, "subtitle": [], "short-title": [], "issued": {"date-parts": [[2022, 11]]}, "references-count": 54, "alternative-id": ["S0148296322005082"], "URL": "http://dx.doi.org/10.1016/j.jbusres.2022.05.066", "relation": {}, "ISSN": ["0148-2963"], "subject": [], "container-title-short": "Journal of Business Research", "published": {"date-parts": [[2022, 11]]}, "assertion": [{"value": "Elsevier", "name": "publisher", "label": "This article is maintained by"}, {"value": "Disruptive innovation: Designing business platforms for new financial services", "name": "articletitle", "label": "Article Title"}, {"value": "Journal of Business Research", "name": "journaltitle", "label": "Journal Title"}, {"value": "https://doi.org/10.1016/j.jbusres.2022.05.066", "name": "articlelink", "label": "CrossRef DOI link to publisher maintained version"}, {"value": "article", "name": "content_type", "label": "Content Type"}, {"value": "\u00a9 2022 Elsevier Inc. All rights reserved.", "name": "copyright", "label": "Copyright"}]}}