{"timestamp": 1771744805.4143207, "ttl_days": 90, "data": {"indexed": {"date-parts": [[2026, 1, 15]], "date-time": "2026-01-15T10:23:35Z", "timestamp": 1768472615284, "version": "3.49.0"}, "reference-count": 81, "publisher": "Elsevier BV", "license": [{"start": {"date-parts": [[2024, 11, 1]], "date-time": "2024-11-01T00:00:00Z", "timestamp": 1730419200000}, "content-version": "tdm", "delay-in-days": 0, "URL": "https://www.elsevier.com/tdm/userlicense/1.0/"}, {"start": {"date-parts": [[2024, 11, 1]], "date-time": "2024-11-01T00:00:00Z", "timestamp": 1730419200000}, "content-version": "tdm", "delay-in-days": 0, "URL": "https://www.elsevier.com/legal/tdmrep-license"}, {"start": {"date-parts": [[2024, 11, 1]], "date-time": "2024-11-01T00:00:00Z", "timestamp": 1730419200000}, "content-version": "vor", "delay-in-days": 0, "URL": "http://creativecommons.org/licenses/by-nc-nd/4.0/"}], "content-domain": {"domain": ["elsevier.com", "sciencedirect.com"], "crossmark-restriction": true}, "published-print": {"date-parts": [[2024, 11]]}, "DOI": "10.1016/j.trip.2024.101271", "type": "journal-article", "created": {"date-parts": [[2024, 11, 11]], "date-time": "2024-11-11T20:08:41Z", "timestamp": 1731355721000}, "page": "101271", "update-policy": "https://doi.org/10.1016/elsevier_cm_policy", "source": "Crossref", "is-referenced-by-count": 1, "special_numbering": "C", "title": "Implications of carbon pricing on food affordability and agri-food sector in Canada: A scoping review", "prefix": "10.1016", "volume": "28", "author": [{"given": "Sylvain", "family": "Charlebois", "sequence": "first", "affiliation": []}, {"given": "Swati", "family": "Saxena", "sequence": "additional", "affiliation": []}, {"given": "Gumataw", "family": "Abebe", "sequence": "additional", "affiliation": []}, {"given": "Tony", "family": "Walker", "sequence": "additional", "affiliation": []}, {"given": "Janet", "family": "Music", "sequence": "additional", "affiliation": []}, {"given": "Vlado", "family": "Keselj", "sequence": "additional", "affiliation": []}, {"given": "Karim", "family": "Tuffaha", "sequence": "additional", "affiliation": []}, {"given": "Keshava", "family": "Pallavi Gone", "sequence": "additional", "affiliation": []}, {"given": "Janele", "family": "Vezeau", "sequence": "additional", "affiliation": []}, {"given": "Bibhuti", "family": "Sarker", "sequence": "additional", "affiliation": []}, {"ORCID": "https://orcid.org/0000-0003-0635-4793", "authenticated-orcid": false, "given": "Stacey", "family": "Taylor", "sequence": "additional", "affiliation": []}], "member": "78", "reference": [{"key": "10.1016/j.trip.2024.101271_b0005", "doi-asserted-by": "crossref", "first-page": "231", "DOI": "10.15826/recon.2020.6.4.020", "article-title": "The Causal Relationship between Agricultural Production, Economic Growth, and Energy Consumption in Ghana", "author": "Ali", "year": "2020", "journal-title": "R-Economy"}, {"issue": "1", "key": "10.1016/j.trip.2024.101271_b0010", "doi-asserted-by": "crossref", "first-page": "19", "DOI": "10.1080/1364557032000119616", "article-title": "Scoping studies: towards a methodological framework", "volume": "8", "author": "Arksey", "year": "2005", "journal-title": "Int. J. Soc. Res. Methodol."}, {"key": "10.1016/j.trip.2024.101271_b0015", "unstructured": "Babiker, M.; Bazaz, A.; Bertoldi, P.; Creutzig, F.; De Coninck, H.; De Kleijne, K.; Dhakal, S.; Haldar, S.; Jiang, K.; K\u0131lk\u0131\u015f, \u015e.; Klaus, I.; Krishnaswamy, J.; Lwasa, S.; Niamir, L.; Pathak, M.; Portugal Pereira, J.; Revi, A.; Roy, J.; Seto, K.; Singh, C.; Some, S.; Steg, L.; \u00dcrge-Vorsatz, D. What the Latest Science on Climate Change Mitigation Means for Cities and Urban Areas; 202. 10.24943/SUPSV310.2022."}, {"issue": "4", "key": "10.1016/j.trip.2024.101271_b0020", "doi-asserted-by": "crossref", "first-page": "545", "DOI": "10.1177/0007650315578450", "article-title": "The drivers of corporate climate change strategies and public policy", "volume": "56", "author": "Backman", "year": "2017", "journal-title": "Bus. Soc."}, {"issue": "1", "key": "10.1016/j.trip.2024.101271_b0025", "first-page": "63", "article-title": "Role of China-Pakistan Economic Corridor in Pakistan\u2019s trade, investment, energy, infrastructure, and stock market", "volume": "16", "author": "Bahoo", "year": "2018", "journal-title": "JISR Manag. Soc. Sci. Econ."}, {"issue": "22", "key": "10.1016/j.trip.2024.101271_b0030", "doi-asserted-by": "crossref", "first-page": "7471", "DOI": "10.3390/en16227471", "article-title": "The comparative analysis of carbon pricing policies on Canadian northwest territories\u2019 economy under different climate change scenarios", "volume": "16", "author": "Berthe", "year": "2023", "journal-title": "Energies"}, {"issue": "1", "key": "10.1016/j.trip.2024.101271_b0035", "doi-asserted-by": "crossref", "first-page": "22", "DOI": "10.1038/s41558-021-01250-z", "article-title": "Potential impacts and challenges of border carbon adjustments", "volume": "12", "author": "B\u00f6hringer", "year": "2022", "journal-title": "Nat. Clim. Chang."}, {"issue": "1", "key": "10.1016/j.trip.2024.101271_b0040", "doi-asserted-by": "crossref", "first-page": "19", "DOI": "10.1016/S0921-8009(00)00173-7", "article-title": "Environmental tax reform: Does it work? A survey of the empirical evidence", "volume": "34", "author": "Bosquet", "year": "2000", "journal-title": "Ecol. Econ."}, {"issue": "4", "key": "10.1016/j.trip.2024.101271_b0045", "doi-asserted-by": "crossref", "first-page": "940", "DOI": "10.1093/erae/jbab019", "article-title": "Tax or green nudge? An experimental analysis of pesticide policies in Germany", "volume": "48", "author": "Buchholz", "year": "2021", "journal-title": "Eur. Rev. Agric. Econ."}, {"key": "10.1016/j.trip.2024.101271_b0050", "doi-asserted-by": "crossref", "DOI": "10.1016/j.resconrec.2022.106278", "article-title": "Literature Review on Policies to Mitigate GHG Emissions for Cement and Concrete", "volume": "182", "author": "Busch", "year": "2022", "journal-title": "Resour. Conserv. Recycl."}, {"issue": "1", "key": "10.1016/j.trip.2024.101271_b0055", "doi-asserted-by": "crossref", "first-page": "34", "DOI": "10.1080/10875549.2015.1094760", "article-title": "An analysis of differences in predictors of food affordability between rural and urban counties", "volume": "20", "author": "Cafer", "year": "2016", "journal-title": "J. Poverty"}, {"key": "10.1016/j.trip.2024.101271_b0060", "unstructured": "Canada, G. of. Estimated Impacts of the Federal Carbon Pollution Pricing System. https://www.canada.ca/en/services/environment/weather/climatechange/climate-action/pricing-carbon-pollution/estimated-impacts-federal-system.html."}, {"key": "10.1016/j.trip.2024.101271_b0065", "doi-asserted-by": "crossref", "first-page": "131", "DOI": "10.1016/j.ecolecon.2018.02.001", "article-title": "Is taxing waste a waste of time? Evidence from a supreme court decision", "volume": "148", "author": "Carattini", "year": "2018", "journal-title": "Ecol. Econ."}, {"issue": "12", "key": "10.1016/j.trip.2024.101271_b0070", "doi-asserted-by": "crossref", "first-page": "772", "DOI": "10.1038/s43016-020-00205-5", "article-title": "Paris Agreement Needs Food System Change", "volume": "1", "author": "Chand", "year": "2020", "journal-title": "Nat. Food"}, {"issue": "1", "key": "10.1016/j.trip.2024.101271_b0075", "doi-asserted-by": "crossref", "first-page": "78", "DOI": "10.3390/nu11010078", "article-title": "Affordability of Food and Beverages in Mexico between 1994 and 2016", "volume": "11", "author": "Colchero", "year": "2019", "journal-title": "Nutrients"}, {"issue": "3", "key": "10.1016/j.trip.2024.101271_b0080", "doi-asserted-by": "crossref", "first-page": "198", "DOI": "10.1038/s43016-021-00225-9", "article-title": "Food Systems Are Responsible for a Third of Global Anthropogenic GHG Emissions", "volume": "2", "author": "Crippa", "year": "2021", "journal-title": "Nat. Food"}, {"key": "10.1016/j.trip.2024.101271_b0085", "first-page": "1290", "article-title": "Carbon pricing in New Zealand: implications for public health", "volume": "122", "author": "Dhar", "year": "2009", "journal-title": "N. Z. Med. J."}, {"key": "10.1016/j.trip.2024.101271_b0090", "unstructured": "Djimeu, E. W.; Nordhagen, S.; Beal, T.; Kelahan, H.; Morris, S. S. Conceptualising and Assessing Food Affordability; GAIN Working Paper 27; 2022."}, {"key": "10.1016/j.trip.2024.101271_b0095", "doi-asserted-by": "crossref", "first-page": "246", "DOI": "10.1016/j.worlddev.2018.11.015", "article-title": "Poverty and distributional effects of carbon pricing in low- and middle-income countries \u2013 a global comparative analysis", "volume": "115", "author": "Dorband", "year": "2019", "journal-title": "World Dev."}, {"key": "10.1016/j.trip.2024.101271_b0100", "doi-asserted-by": "crossref", "DOI": "10.1016/j.landusepol.2021.105320", "article-title": "Effects of a carbon tax in the United States on agricultural markets and carbon emissions from land-use change", "volume": "103", "author": "Dumortier", "year": "2021", "journal-title": "Land Use Policy"}, {"issue": "2", "key": "10.1016/j.trip.2024.101271_b0105", "doi-asserted-by": "crossref", "DOI": "10.1088/1748-9326/7/2/024023", "article-title": "The effects of potential changes in United States beef production on global grazing systems and greenhouse gas emissions", "volume": "7", "author": "Dumortier", "year": "2012", "journal-title": "Environ. Res. Lett."}, {"issue": "6", "key": "10.1016/j.trip.2024.101271_b0110", "doi-asserted-by": "crossref", "first-page": "766", "DOI": "10.1016/j.jmoneco.2009.06.001", "article-title": "How sensitive are consumer expenditures to retail energy prices?", "volume": "56", "author": "Edelstein", "year": "2009", "journal-title": "J. Monet. Econ."}, {"key": "10.1016/j.trip.2024.101271_b0115", "unstructured": "Elbedawi, M. M. Food Security and Environmental Implications of Carbon Pricing in High-Income Regions, Colorado Boulder, 2022. file:///C:/Users/sbks0/OneDrive/Desktop/New folder/Mohamed_Elbedawi_Final_Thesis.pdf."}, {"key": "10.1016/j.trip.2024.101271_b0120", "series-title": "Pricing Carbon: The European Union Emissions Trading Scheme", "author": "Ellerman", "year": "2010"}, {"issue": "4", "key": "10.1016/j.trip.2024.101271_b0125", "doi-asserted-by": "crossref", "first-page": "918", "DOI": "10.1111/j.1467-8276.2008.01158.x", "article-title": "Removing distortions in the U.S. ethanol market: what does it imply for the United States and Brazil?", "volume": "90", "author": "Elobeid", "year": "2008", "journal-title": "Am. J. Agric. Econ."}, {"issue": "2", "key": "10.1016/j.trip.2024.101271_b0130", "doi-asserted-by": "crossref", "first-page": "263", "DOI": "10.1016/S0921-8009(00)00236-6", "article-title": "Pesticide taxation and multi-objective policy-making: farm modelling to evaluate profit/environment trade-offs", "volume": "36", "author": "Falconer", "year": "2001", "journal-title": "Ecol. Econ."}, {"key": "10.1016/j.trip.2024.101271_b0135", "unstructured": "FAO. FAO Food Price Index; 2024. https://www.fao.org/worldfoodsituation/foodpricesindex/en/."}, {"key": "10.1016/j.trip.2024.101271_b0140", "unstructured": "Fraser, E.; Newman, L. Food is too expensive, but don\u2019t blame climate policy. Financial Post."}, {"issue": "2", "key": "10.1016/j.trip.2024.101271_b0145", "doi-asserted-by": "crossref", "first-page": "303", "DOI": "10.1257/app.20180474", "article-title": "Energy Cost Pass-Through in US Manufacturing: Estimates and Implications for Carbon Taxes", "volume": "12", "author": "Ganapati", "year": "2020", "journal-title": "Am. Econ. J. Appl. Econ."}, {"issue": "3", "key": "10.1016/j.trip.2024.101271_b0150", "doi-asserted-by": "crossref", "first-page": "367", "DOI": "10.1007/s11158-022-09569-w", "article-title": "Backward-looking principles of climate justice: the unjustified move from the polluter pays principle to the beneficiary pays principle", "volume": "29", "author": "Garc\u00eda-Portela", "year": "2023", "journal-title": "Res Publica"}, {"key": "10.1016/j.trip.2024.101271_b0155", "doi-asserted-by": "crossref", "DOI": "10.1016/j.tifs.2024.104577", "article-title": "Carbon pricing and the food system: implications for sustainability and equity", "volume": "150", "author": "Habib", "year": "2024", "journal-title": "Trends Food Sci. Technol."}, {"key": "10.1016/j.trip.2024.101271_b0160", "doi-asserted-by": "crossref", "unstructured": "Hamilton, J. Macroeconomics and ARCH; Cambridge, MA, 2008. 10.3386/w14151.", "DOI": "10.3386/w14151"}, {"issue": "10218", "key": "10.1016/j.trip.2024.101271_b0165", "doi-asserted-by": "crossref", "first-page": "142", "DOI": "10.1016/S0140-6736(19)32506-1", "article-title": "Double-duty actions: seizing programme and policy opportunities to address malnutrition in all its forms", "volume": "395", "author": "Hawkes", "year": "2020", "journal-title": "Lancet"}, {"key": "10.1016/j.trip.2024.101271_b0170", "unstructured": "Health Canada. National Nutritious Food Basket. https://www.canada.ca/en/health-canada/services/food-nutrition/food-nutrition-surveillance/national-nutritious-food-basket.html."}, {"key": "10.1016/j.trip.2024.101271_b0175", "doi-asserted-by": "crossref", "DOI": "10.1016/j.euroecorev.2020.103440", "article-title": "\u201cCarbon Pricing\u201d special issue in the european economic review", "volume": "127", "author": "Hepburn", "year": "2020", "journal-title": "Eur. Econ. Rev."}, {"issue": "3", "key": "10.1016/j.trip.2024.101271_b0180", "doi-asserted-by": "crossref", "first-page": "505", "DOI": "10.1007/s12571-015-0455-8", "article-title": "The food environment, its effects on dietary consumption, and potential for measurement within agriculture-nutrition interventions", "volume": "7", "author": "Herforth", "year": "2015", "journal-title": "Food Secur."}, {"key": "10.1016/j.trip.2024.101271_b0190", "unstructured": "IPCC. Sixth Assessment Report; 2023."}, {"issue": "2", "key": "10.1016/j.trip.2024.101271_b0195", "doi-asserted-by": "crossref", "first-page": "409", "DOI": "10.1007/s10018-020-00293-4", "article-title": "Increasing food production and mitigating agricultural greenhouse gas emissions in the European union: impacts of carbon pricing and calorie production targeting", "volume": "23", "author": "Isbasoiu", "year": "2021", "journal-title": "Environ. Econ. Policy Stud."}, {"issue": "6600", "key": "10.1016/j.trip.2024.101271_b0200", "doi-asserted-by": "crossref", "first-page": "1401", "DOI": "10.1126/science.abo4207", "article-title": "How trade policy can support the climate agenda", "volume": "376", "author": "Jakob", "year": "2022", "journal-title": "Science (80-.)"}, {"issue": "3", "key": "10.1016/j.trip.2024.101271_b0205", "doi-asserted-by": "crossref", "first-page": "356", "DOI": "10.1080/19320248.2014.962769", "article-title": "The Capacity Building Experience of Women Engaged in Determining the Cost and Affordability of Healthy Food in Nova Scotia", "volume": "10", "author": "Johnson", "year": "2015", "journal-title": "Canada. J. Hunger Environ. Nutr."}, {"issue": "16", "key": "10.1016/j.trip.2024.101271_b0210", "doi-asserted-by": "crossref", "first-page": "6463", "DOI": "10.3390/su12166463", "article-title": "Sustainable development in the agri-food sector in terms of the carbon footprint: A review", "volume": "12", "author": "Karwacka", "year": "2020", "journal-title": "Sustainability"}, {"key": "10.1016/j.trip.2024.101271_b0215", "article-title": "The effectiveness, efficiency and equity of market based and voluntary measures to mitigate greenhouse gas emissions from the agri-food sector", "author": "Kasterine", "year": "2010", "journal-title": "UNCTAD Trade Environ. Rev."}, {"issue": "031", "key": "10.1016/j.trip.2024.101271_b0220", "doi-asserted-by": "crossref", "first-page": "1", "DOI": "10.5089/9798400267277.001", "article-title": "Carbon prices and inflation in the Euro Area", "volume": "2024", "author": "Konradt", "year": "2024", "journal-title": "IMF Work. Pap."}, {"issue": "6", "key": "10.1016/j.trip.2024.101271_b0225", "doi-asserted-by": "crossref", "first-page": "2518", "DOI": "10.1093/jeea/jvad020", "article-title": "Carbon taxation and greenflation: evidence from Europe and Canada", "volume": "21", "author": "Konradt", "year": "2023", "journal-title": "J. Eur. Econ. Assoc."}, {"key": "10.1016/j.trip.2024.101271_b0230", "series-title": "Handbook of Public Economics", "doi-asserted-by": "crossref", "first-page": "1471", "DOI": "10.1016/S1573-4420(02)80027-1", "article-title": "Environmental taxation and regulation", "author": "Lans Bovenberg", "year": "2002"}, {"issue": "6", "key": "10.1016/j.trip.2024.101271_b0235", "doi-asserted-by": "crossref", "first-page": "1255", "DOI": "10.3390/ijerph15061255", "article-title": "Cost and affordability of diets modelled on current eating patterns and on dietary guidelines, for New Zealand total population, m\u0101ori and pacific households", "volume": "15", "author": "Mackay", "year": "2018", "journal-title": "Int. J. Environ. Res. Public Health"}, {"key": "10.1016/j.trip.2024.101271_b0240", "doi-asserted-by": "crossref", "first-page": "31", "DOI": "10.1016/j.foodpol.2016.12.007", "article-title": "Assessing food value chain pathways, linkages and impacts for better nutrition of vulnerable groups", "volume": "68", "author": "Maestre", "year": "2017", "journal-title": "Food Policy"}, {"key": "10.1016/j.trip.2024.101271_b0245", "unstructured": "Mbow, C.; Rosenzweig, C.; Barioni, L. G.; Benton, T. G.; Herrero, M.; Krishnapillai, M.; Liwenga, E.; Pradhan, P.; Rivera-Ferre, M. G.; Sapkota, T.; Tubiello, F. N.; Xu, Y. Food Security. In Climate Change and Land: an IPCC special report on climate change, desertification, land degradation, sustainable land management, food security, and greenhouse gas fluxes in terrestrial ecosystems; Shukla, P. R., Skea, J., Buendia, E. C., Masson-Delmotte, V., P\u00f6rtner, H.-O., Roberts, D. C., Zhai, P., Slade, R., Connors, S., Diemen, R. van, Ferrat, M., Haughey, E., Luz, S., Neogi, S., Pathak, M., Petzold, J., Pereira, J. P., Vyas, P., Huntley, E., Kissick, K., Belkacemi, M., Malley, J., Eds.; NTRS, 2020."}, {"issue": "4", "key": "10.1016/j.trip.2024.101271_b0250", "first-page": "753", "article-title": "The Impact of Global Warming on Agriculture: A Ricardian Analysis", "volume": "84", "author": "Mendelsohn", "year": "1994", "journal-title": "Am. Econ. Rev."}, {"issue": "3", "key": "10.1016/j.trip.2024.101271_b0255", "doi-asserted-by": "crossref", "first-page": "407", "DOI": "10.1093/aepp/ppx028", "article-title": "Labeling food processes: the good, the bad and the ugly", "volume": "39", "author": "Messer", "year": "2017", "journal-title": "Appl. Econ. Perspect. Policy"}, {"key": "10.1016/j.trip.2024.101271_b0260", "doi-asserted-by": "crossref", "unstructured": "Moessner, R. Effects of Carbon Pricing on Inflation; CESifo Working Paper; 9563; 2022.", "DOI": "10.2139/ssrn.4033600"}, {"key": "10.1016/j.trip.2024.101271_b0265", "series-title": "Transforming Food Systems: Ethics, Innovation and Responsibility", "first-page": "186", "article-title": "Carbon Price and Be Damned", "author": "Moran", "year": "2022"}, {"key": "10.1016/j.trip.2024.101271_b0270", "series-title": "CESifo Working Paper", "article-title": "Carbon Pricing and Inflation Expectations: Evidence from France", "author": "Moretti", "year": "2023"}, {"issue": "3", "key": "10.1016/j.trip.2024.101271_b0275", "doi-asserted-by": "crossref", "first-page": "e158", "DOI": "10.17269/cjph.105.4322", "article-title": "Is the minimum enough? Affordability of a nutritious diet for minimum wage earners in Nova Scotia (2002\u20132012)", "volume": "105", "author": "Newell", "year": "2014", "journal-title": "Can. J. Public Heal."}, {"issue": "3\u20134", "key": "10.1016/j.trip.2024.101271_b0280", "doi-asserted-by": "crossref", "first-page": "393", "DOI": "10.1111/cjag.12341", "article-title": "Canadian food inflation: international dynamics and local agency", "volume": "71", "author": "Nu\u00f1o-Ledesma", "year": "2023", "journal-title": "Can. J. Agric. Econ. Can. D\u2019agroeconomie"}, {"key": "10.1016/j.trip.2024.101271_b0290", "doi-asserted-by": "crossref", "first-page": "85", "DOI": "10.1016/j.iheduc.2015.02.002", "article-title": "The use of flipped classrooms in higher education: A scoping review", "volume": "25", "author": "O\u2019Flaherty", "year": "2015", "journal-title": "Internet High. Educ."}, {"issue": "2", "key": "10.1016/j.trip.2024.101271_b0295", "doi-asserted-by": "crossref", "first-page": "605", "DOI": "10.1007/s10640-019-00337-8", "article-title": "The effect of carbon tax on farm income: evidence from a Canadian Province", "volume": "74", "author": "Olale", "year": "2019", "journal-title": "Environ. Resour. Econ."}, {"key": "10.1016/j.trip.2024.101271_b0300", "doi-asserted-by": "crossref", "DOI": "10.1016/j.foodpol.2020.101982", "article-title": "Affordability of nutritious diets in rural India", "volume": "99", "author": "Raghunathan", "year": "2021", "journal-title": "Food Policy"}, {"issue": "4", "key": "10.1016/j.trip.2024.101271_b0305", "first-page": "899", "article-title": "The distribution of costs of a carbon tax among Canadian households", "volume": "60", "author": "Rivers", "year": "2012", "journal-title": "Can. Tax J."}, {"issue": "1", "key": "10.1016/j.trip.2024.101271_b0310", "doi-asserted-by": "crossref", "first-page": "13", "DOI": "10.1111/1747-0080.12142", "article-title": "Access and affordability of nutritious food in metropolitan <scp>M</Scp> Elbourne", "volume": "73", "author": "Rossimel", "year": "2016", "journal-title": "Nutr. Diet."}, {"issue": "1", "key": "10.1016/j.trip.2024.101271_b0315", "doi-asserted-by": "crossref", "first-page": "113", "DOI": "10.1162/rest.2006.88.1.113", "article-title": "The Impact of Global Warming on U.S. Agriculture: An Econometric Analysis of Optimal Growing Conditions", "volume": "88", "author": "Schlenker", "year": "2006", "journal-title": "Rev. Econ. Stat."}, {"issue": "8", "key": "10.1016/j.trip.2024.101271_b0320", "doi-asserted-by": "crossref", "first-page": "481", "DOI": "10.1038/s43016-020-0128-4", "article-title": "Adoption of the \u2018Planetary Health Diet\u2019 Has Different Impacts on Countries\u2019 Greenhouse Gas Emissions", "volume": "1", "author": "Semba", "year": "2020", "journal-title": "Nat. Food"}, {"issue": "2", "key": "10.1016/j.trip.2024.101271_b0325", "doi-asserted-by": "crossref", "first-page": "305", "DOI": "10.1111/cjag.12157", "article-title": "The effects of pricing canadian livestock emissions", "volume": "66", "author": "Slade", "year": "2018", "journal-title": "Can. J. Agric. Econ. Can. D\u2019agroeconomie"}, {"key": "10.1016/j.trip.2024.101271_b0330", "unstructured": "Statistics Canada. Consumer Price Index; 2022."}, {"key": "10.1016/j.trip.2024.101271_b0335", "article-title": "Carbon Taxes vs Cap and Trade", "author": "Stavins", "year": "2019", "journal-title": "Theory and Practice"}, {"issue": "2", "key": "10.1016/j.trip.2024.101271_b0340", "doi-asserted-by": "crossref", "first-page": "313", "DOI": "10.1093/reep/ret008", "article-title": "Reflections\u2014carbon pricing in practice", "volume": "7", "author": "Tietenberg", "year": "2013", "journal-title": "Rev. Environ. Econ. Policy"}, {"issue": "4", "key": "10.1016/j.trip.2024.101271_b0345", "doi-asserted-by": "crossref", "first-page": "1456", "DOI": "10.1257/jel.20211560", "article-title": "Carbon taxes", "volume": "60", "author": "Timilsina", "year": "2022", "journal-title": "J. Econ. Lit."}, {"issue": "2", "key": "10.1016/j.trip.2024.101271_b0350", "doi-asserted-by": "crossref", "first-page": "387", "DOI": "10.1093/advances/nmz031", "article-title": "Food environment research in low- and middle-income countries: a systematic scoping review", "volume": "11", "author": "Turner", "year": "2020", "journal-title": "Adv. Nutr."}, {"issue": "10", "key": "10.1016/j.trip.2024.101271_b0355", "doi-asserted-by": "crossref", "first-page": "941", "DOI": "10.1038/s41893-019-0385-0", "article-title": "Cash transfers for pro-poor carbon taxes in Latin America and the Caribbean", "volume": "2", "author": "Vogt-Schilb", "year": "2019", "journal-title": "Nat. Sustain."}, {"issue": "1", "key": "10.1016/j.trip.2024.101271_b0360", "doi-asserted-by": "crossref", "first-page": "36", "DOI": "10.1007/BF03404415", "article-title": "The affordability of a nutritious diet for households on welfare in Toronto", "volume": "93", "author": "Vozoris", "year": "2002", "journal-title": "Can. J. Public Heal."}, {"key": "10.1016/j.trip.2024.101271_b0365", "article-title": "Is the carbon tax an easy scapegoat for high food prices?", "author": "Wherry", "year": "2023", "journal-title": "CBC News"}, {"issue": "11", "key": "10.1016/j.trip.2024.101271_b0370", "doi-asserted-by": "crossref", "first-page": "1132", "DOI": "10.3390/nu2111132", "article-title": "Monitoring the affordability of healthy eating: A case study of 10 years of the Illawarra Healthy Food Basket", "volume": "2", "author": "Williams", "year": "2010", "journal-title": "Nutrients"}, {"issue": "3", "key": "10.1016/j.trip.2024.101271_b0375", "doi-asserted-by": "crossref", "first-page": "183", "DOI": "10.1007/BF03403810", "article-title": "Afford ability of a nutritious diet for income assistance recipients in Nova Scotia (2002\u20132010)", "volume": "103", "author": "Williams", "year": "2012", "journal-title": "Can. J. Public Heal."}, {"issue": "1", "key": "10.1016/j.trip.2024.101271_b0380", "doi-asserted-by": "crossref", "first-page": "13", "DOI": "10.3138/cpp.2022-036", "article-title": "Carbon Pricing costs for households and the progressivity of revenue recycling options in Canada", "volume": "49", "author": "Winter", "year": "2023", "journal-title": "Can. Public Policy"}, {"issue": "1", "key": "10.1016/j.trip.2024.101271_b0385", "doi-asserted-by": "crossref", "first-page": "8", "DOI": "10.1111/j.1747-0080.2010.01490.x", "article-title": "Availability, affordability and quality of a healthy food basket in Adelaide, South Australia", "volume": "68", "author": "Wong", "year": "2011", "journal-title": "Nutr. Diet."}, {"key": "10.1016/j.trip.2024.101271_b0390", "series-title": "27th annual meeting of the Canadian Resource and Environmental Economics Study Group; London, Ontario", "article-title": "Did Ontario\u2019s emission permit trading policy reduce emissions?", "author": "Wood", "year": "2017"}, {"key": "10.1016/j.trip.2024.101271_b0395", "unstructured": "World Health Organization. Nutrition. https://www.who.int/health-topics/nutrition#tab=tab_1."}, {"key": "10.1016/j.trip.2024.101271_b0400", "series-title": "International Association of Agricultural Economists (IAAE)", "article-title": "The impact of carbon tax on food prices and consumption in Canada", "author": "Wu", "year": "2018"}, {"key": "10.1016/j.trip.2024.101271_b0405", "doi-asserted-by": "crossref", "first-page": "4093", "DOI": "10.1016/j.jclepro.2015.08.081", "article-title": "Joint production and pricing decisions for multiple products with cap-and-trade and carbon tax regulations", "volume": "112", "author": "Xu", "year": "2016", "journal-title": "J. Clean. Prod."}, {"issue": "1", "key": "10.1016/j.trip.2024.101271_b0410", "doi-asserted-by": "crossref", "first-page": "198", "DOI": "10.1038/s41467-023-44464-9", "article-title": "Diversifying Crop Rotation Increases Food Production, Reduces Net Greenhouse Gas Emissions and Improves Soil Health", "volume": "15", "author": "Yang", "year": "2024", "journal-title": "Nat Comm."}, {"key": "10.1016/j.trip.2024.101271_b0415", "doi-asserted-by": "crossref", "DOI": "10.1016/j.ecolecon.2023.108082", "article-title": "Assessing the distributional impacts of ambitious carbon pricing in China\u2019s agricultural sector", "volume": "217", "author": "Zhang", "year": "2024", "journal-title": "Ecol. Econ."}], "container-title": "Transportation Research Interdisciplinary Perspectives", "original-title": [], "language": "en", "link": [{"URL": "https://api.elsevier.com/content/article/PII:S2590198224002574?httpAccept=text/xml", "content-type": "text/xml", "content-version": "vor", "intended-application": "text-mining"}, {"URL": "https://api.elsevier.com/content/article/PII:S2590198224002574?httpAccept=text/plain", "content-type": "text/plain", "content-version": "vor", "intended-application": "text-mining"}], "deposited": {"date-parts": [[2024, 12, 17]], "date-time": "2024-12-17T12:18:57Z", "timestamp": 1734437937000}, "score": 1, "resource": {"primary": {"URL": "https://linkinghub.elsevier.com/retrieve/pii/S2590198224002574"}}, "subtitle": [], "short-title": [], "issued": {"date-parts": [[2024, 11]]}, "references-count": 81, "alternative-id": ["S2590198224002574"], "URL": "http://dx.doi.org/10.1016/j.trip.2024.101271", "relation": {}, "ISSN": ["2590-1982"], "subject": [], "container-title-short": "Transportation Research Interdisciplinary Perspectives", "published": {"date-parts": [[2024, 11]]}, "assertion": [{"value": "Elsevier", "name": "publisher", "label": "This article is maintained by"}, {"value": "Implications of carbon pricing on food affordability and agri-food sector in Canada: A scoping review", "name": "articletitle", "label": "Article Title"}, {"value": "Transportation Research Interdisciplinary Perspectives", "name": "journaltitle", "label": "Journal Title"}, {"value": "https://doi.org/10.1016/j.trip.2024.101271", "name": "articlelink", "label": "CrossRef DOI link to publisher maintained version"}, {"value": "article", "name": "content_type", "label": "Content Type"}, {"value": "\u00a9 2024 The Authors. Published by Elsevier Ltd.", "name": "copyright", "label": "Copyright"}], "article-number": "101271"}}