{"timestamp": 1771706954.6575708, "ttl_days": 30, "data": {"results": [{"publisher": "SAGE Publications", "issue": "6", "published-print": {"date-parts": [[2023, 12]]}, "DOI": "10.1177/01655515221074323", "type": "journal-article", "page": "1692-1710", "title": ["Collaboration of issuing agencies and topic evolution of health informatisation policies in China"], "volume": "49", "author": [{"ORCID": "https://orcid.org/0000-0001-9077-4189", "authenticated-orcid": false, "given": "Wenli", "family": "Zhang", "sequence": "first", "affiliation": [{"name": "School of Medicine and Health Management, Tongji Medical College, Huazhong University of Science and Technology, China; Hubei Provincial Research Center for Health Technology Assessment, China; Institute of Smart Health, Huazhong University of Science and Technology, China"}]}, {"ORCID": "https://orcid.org/0000-0002-2315-688X", "authenticated-orcid": false, "given": "Rui", "family": "Yao", "sequence": "additional", "affiliation": [{"name": "School of Medicine and Health Management, Tongji Medical College, Huazhong University of Science and Technology, China"}]}, {"ORCID": "https://orcid.org/0000-0001-6367-0560", "authenticated-orcid": false, "given": "Richard", "family": "Evans", "sequence": "additional", "affiliation": [{"name": "Faculty of Computer Science, Dalhousie University, Canada"}]}, {"ORCID": "https://orcid.org/0000-0001-6289-2145", "authenticated-orcid": false, "given": "Wenjing", "family": "Huang", "sequence": "additional", "affiliation": [{"name": "School of Medicine and Health Management, Tongji Medical College, Huazhong University of Science and Technology, China"}]}, {"ORCID": "https://orcid.org/0000-0001-5015-2115", "authenticated-orcid": false, "given": "Guang", "family": "Cao", "sequence": "additional", "affiliation": [{"name": "School of Medicine and Health Management, Tongji Medical College, Huazhong University of Science and Technology, China"}]}, {"ORCID": "https://orcid.org/0000-0002-7311-8777", "authenticated-orcid": false, "given": "Lining", "family": "Shen", "sequence": "additional", "affiliation": [{"name": "School of Medicine and Health Management, Tongji Medical College, Huazhong University of Science and Technology, China; Institute of Smart Health, Huazhong University of Science and Technology, China"}]}], "published-online": {"date-parts": [[2022, 2, 24]]}, "container-title": ["Journal of Information Science"], "issued": {"date-parts": [[2022, 2, 24]]}, "URL": "https://doi.org/10.1177/01655515221074323"}]}}